{
    "piped": [
        "https://nyc1.piapi.ggtyler.dev",
        "https://pipedapi.darkness.services",
        "https://piapi.ggtyler.dev",
        "https://pipedapi.ducks.party",
        "https://pipedapi.reallyaweso.me",
        "https://pipedapi.adminforge.de"
    ],
    "hls": [
        "https://pipedapi.nosebs.ru",
        "https://pipedapi.orangenet.cc",
        "https://pipedapi.leptons.xyz",
        "https://api.piped.private.coffee",
        "https://cal1.piapi.ggtyler.dev",
        "https://pol1.piapi.ggtyler.dev"
    ],
    "invidious": [
        "https://id.420129.xyz"
    ],
    "hyperpipe": "https://hpapi.ggtyler.dev",
    "status": 0
}